sklabs/__init__.py
sklabs/bess_base.py
sklabs/datasets.py
sklabs/functions.py
sklabs/linear.py
sklabs/metrics.py
sklabs/pybind_cabess.cpython-36m-darwin.so
sklabs/utilities.py
scikit_labs-0.0.1rc2.dist-info/LICENSE
scikit_labs-0.0.1rc2.dist-info/METADATA
scikit_labs-0.0.1rc2.dist-info/WHEEL
scikit_labs-0.0.1rc2.dist-info/top_level.txt
scikit_labs-0.0.1rc2.dist-info/RECORD
