Metadata-Version: 2.1
Name: scikit-labs
Version: 0.0.1rc2
Summary: LABS: Linear-time Adaptive Best-subset Selection
Download-URL: https://pypi.python.org/pypi/scikit-labs
Author: Jin Zhu, Junxian Zhu, Junhao Huang, Xueqin Wang, Heping Zhang
License: GPL-3
Project-URL: Bug Tracker, https://github.com/abess-team/scikit-labs/issues
Project-URL: Source Code, https://github.com/abess-team/scikit-labs
Classifier: Intended Audience :: Science/Research
Classifier: Intended Audience :: Developers
Classifier: Programming Language :: C++
Classifier: Programming Language :: Python
Classifier: Topic :: Software Development
Classifier: Topic :: Scientific/Engineering
Classifier: Topic :: Scientific/Engineering :: Artificial Intelligence
Classifier: Topic :: Scientific/Engineering :: Mathematics
Classifier: Operating System :: Microsoft :: Windows
Classifier: Operating System :: POSIX :: Linux
Classifier: Operating System :: MacOS
Classifier: Programming Language :: Python
Classifier: Programming Language :: Python :: 3.6
Classifier: Programming Language :: Python :: 3.7
Classifier: Programming Language :: Python :: 3.8
Classifier: Programming Language :: Python :: 3.9
Classifier: Programming Language :: Python :: 3.10
Classifier: Programming Language :: Python :: 3.11
Requires-Python: >=3.6
License-File: LICENSE
Requires-Dist: numpy
Requires-Dist: pandas
Requires-Dist: scipy
Requires-Dist: scikit-learn >=0.24
